pyfdm/__init__.py
pyfdm/correlations.py
pyfdm/helpers.py
pyfdm/weights.py
pyfdm/methods/__init__.py
pyfdm/methods/f_aras.py
pyfdm/methods/f_codas.py
pyfdm/methods/f_copras.py
pyfdm/methods/f_edas.py
pyfdm/methods/f_mabac.py
pyfdm/methods/f_mairca.py
pyfdm/methods/f_moora.py
pyfdm/methods/f_ocra.py
pyfdm/methods/f_topsis.py
pyfdm/methods/f_vikor.py
pyfdm/methods/validator.py
pyfdm/methods/aras/__init__.py
pyfdm/methods/aras/fuzzy.py
pyfdm/methods/codas/__init__.py
pyfdm/methods/codas/fuzzy.py
pyfdm/methods/copras/__init__.py
pyfdm/methods/copras/fuzzy.py
pyfdm/methods/edas/__init__.py
pyfdm/methods/edas/fuzzy.py
pyfdm/methods/fuzzy_sets/__init__.py
pyfdm/methods/fuzzy_sets/tfn/__init__.py
pyfdm/methods/fuzzy_sets/tfn/defuzzifications.py
pyfdm/methods/fuzzy_sets/tfn/distances.py
pyfdm/methods/fuzzy_sets/tfn/normalizations.py
pyfdm/methods/mabac/__init__.py
pyfdm/methods/mabac/fuzzy.py
pyfdm/methods/mairca/__init__.py
pyfdm/methods/mairca/fuzzy.py
pyfdm/methods/moora/__init__.py
pyfdm/methods/moora/fuzzy.py
pyfdm/methods/ocra/__init__.py
pyfdm/methods/ocra/fuzzy.py
pyfdm/methods/topsis/__init__.py
pyfdm/methods/topsis/fuzzy.py
pyfdm/methods/vikor/__init__.py
pyfdm/methods/vikor/fuzzy.py
pyfdm-1.0.2.dist-info/LICENSE
pyfdm-1.0.2.dist-info/METADATA
pyfdm-1.0.2.dist-info/WHEEL
pyfdm-1.0.2.dist-info/top_level.txt
pyfdm-1.0.2.dist-info/RECORD
