Metadata-Version: 2.1
Name: pyfdm
Version: 1.0.2
Summary: Python library for Fuzzy Decision Making
Home-page: https://github.com/jwieckowski/pyfdm
Author: Jakub Więckowski
Author-email: jakub-wieckowski@zut.edu.pl
Classifier: Programming Language :: Python :: 3
Classifier: License :: OSI Approved :: MIT License
Classifier: Operating System :: OS Independent
Requires-Python: >=3.7
License-File: LICENSE
Requires-Dist: numpy
Requires-Dist: scipy
